cvebase_wiki/__init__.py
cvebase_wiki/__main__.py
cvebase_wiki/cvebase_wiki.py
cvebase_wiki/edit.py
cvebase_wiki/generate.py
cvebase_wiki/lint.py
cvebase_wiki-0.1.5.dist-info/entry_points.txt
cvebase_wiki-0.1.5.dist-info/LICENSE
cvebase_wiki-0.1.5.dist-info/WHEEL
cvebase_wiki-0.1.5.dist-info/METADATA
cvebase_wiki-0.1.5.dist-info/RECORD
